leibniz/__init__.py
leibniz/core2d/__init__.py
leibniz/core2d/element.py
leibniz/core2d/ops.py
leibniz/core2d/vec2.py
leibniz/core3d/__init__.py
leibniz/core3d/element.py
leibniz/core3d/ops.py
leibniz/core3d/vec3.py
leibniz/core3d/basis/__init__.py
leibniz/core3d/basis/lng_lat_alt.py
leibniz/core3d/basis/phi_rho.py
leibniz/core3d/basis/theta_phi_r.py
leibniz/core3d/basis/x_y.py
leibniz/core3d/basis/x_y_z.py
leibniz/core3d/diffr/__init__.py
leibniz/core3d/diffr/regular3.py
leibniz/core3d/frame/__init__.py
leibniz/core3d/frame/thetaphir.py
leibniz/core3d/frame/xyz.py
leibniz/core3d/gridsys/__init__.py
leibniz/core3d/gridsys/regular2.py
leibniz/core3d/gridsys/regular3.py
leibniz/diffeq/__init__.py
leibniz/diffeq/_impl/__init__.py
leibniz/diffeq/_impl/adams.py
leibniz/diffeq/_impl/adjoint.py
leibniz/diffeq/_impl/dopri5.py
leibniz/diffeq/_impl/fixed_adams.py
leibniz/diffeq/_impl/fixed_grid.py
leibniz/diffeq/_impl/interp.py
leibniz/diffeq/_impl/misc.py
leibniz/diffeq/_impl/odeint.py
leibniz/diffeq/_impl/rk_common.py
leibniz/diffeq/_impl/solvers.py
leibniz/diffeq/_impl/tsit5.py
leibniz/nn/__init__.py
leibniz/nn/activation.py
leibniz/nn/conv.py
leibniz/nn/dropout.py
leibniz/nn/normalizor.py
leibniz/nn/pooling.py
leibniz/nn/sampling.py
leibniz/nn/layer/__init__.py
leibniz/nn/layer/cbam.py
leibniz/nn/layer/hyperbolic.py
leibniz/nn/layer/hyperbolic2.py
leibniz/nn/layer/residual.py
leibniz/nn/layer/senet.py
leibniz/nn/layer/simam.py
leibniz/nn/layer/warp.py
leibniz/nn/net/__init__.py
leibniz/nn/net/conv_lstm.py
leibniz/nn/net/hunet.py
leibniz/nn/net/hyptube.py
leibniz/nn/net/mlp.py
leibniz/nn/net/resnet.py
leibniz/nn/net/resnetz.py
leibniz/nn/net/simple.py
leibniz/nn/net/unet.py
leibniz/nn/net/unet2.py
leibniz/nn/net/unet3.py
leibniz/nn/net/unetz.py
samples/__init__.py
samples/simple_advection.py
samples/simple_rotation.py
samples/simple_rotation_with_intg.py
leibniz-0.2.0.dist-info/LICENSE
leibniz-0.2.0.dist-info/METADATA
leibniz-0.2.0.dist-info/WHEEL
leibniz-0.2.0.dist-info/top_level.txt
leibniz-0.2.0.dist-info/RECORD
