Metadata-Version: 2.1
Name: leibniz
Version: 0.2.0
Summary: Leibniz: a package providing facilities to express learnable differential equations based on PyTorch
Home-page: https://github.com/mountain/leibniz
Author: Mingli Yuan
Author-email: mingli.yuan@gmail.com
Project-URL: Documentation, https://github.com/mountain/leibniz
Project-URL: Source, https://github.com/mountain/leibniz
Project-URL: Tracker, https://github.com/mountain/leibniz/issues
Classifier: Programming Language :: Python :: 3
Classifier: License :: OSI Approved :: MIT License
Classifier: Operating System :: OS Independent
Requires-Python: >=3.9
License-File: LICENSE
Requires-Dist: cached-property
Requires-Dist: torchpwl
Requires-Dist: torch
Requires-Dist: numpy
